lstid_processing/__init__.py
lstid_processing/cindi.py
lstid_processing/plot_rout.py
lstid_processing/map_files/igrf10.inc_equator
lstid_processing/model/__init__.py
lstid_processing/model/analysis.py
lstid_processing/model/io.py
lstid_processing/model/plots.py
lstid_processing/smoothing/__init__.py
lstid_processing/smoothing/fill_rout.py
lstid_processing/smoothing/filter_rout.py
lstid_processing-0.0.1.dist-info/licenses/LICENSE
lstid_processing-0.0.1.dist-info/METADATA
lstid_processing-0.0.1.dist-info/WHEEL
lstid_processing-0.0.1.dist-info/top_level.txt
lstid_processing-0.0.1.dist-info/RECORD
