Metadata-Version: 2.4
Name: lstid_processing
Version: 0.0.1
Summary: Identify TIDs in CINDI and process SAMI3 data
Maintainer-email: "Angeline G. Burrell" <angeline.g.burrell.civ@us.navy.mil>
License: The MIT License (MIT)
Project-URL: source, https://github.com/aburrell/lstid_processing
Project-URL: documentation, https://lstid_processing.readthedocs.io/en/latest/
Project-URL: tracker, https://github.com/aburrell/lstid_processing/issues
Project-URL: download, https://github.com/aburrell/lstid_processing/releases
Keywords: travelling ionospheric disturbances,traveling ionospheric disturbances,TIDs,C/NOFS,pysat,ionosphere,atmosphere,thermosphere,CINDI,SAMI3,heliosphere,observations,space,satellites,analysis
Classifier: Development Status :: 3 - Alpha
Classifier: Intended Audience :: Science/Research
Classifier: Topic :: Scientific/Engineering :: Atmospheric Science
Classifier: Topic :: Scientific/Engineering :: Physics
Classifier: Natural Language :: English
Classifier: Programming Language :: Python
Classifier: Programming Language :: Python :: 3
Classifier: Programming Language :: Python :: 3.10
Classifier: Programming Language :: Python :: 3.11
Classifier: Programming Language :: Python :: 3.12
Classifier: Programming Language :: Python :: 3.13
Classifier: Operating System :: Unix
Classifier: Operating System :: POSIX
Classifier: Operating System :: POSIX :: Linux
Classifier: Operating System :: MacOS :: MacOS X
Classifier: Operating System :: Microsoft :: Windows
Requires-Python: >=3.10
License-File: LICENSE
Requires-Dist: cmocean
Requires-Dist: matplotlib
Requires-Dist: numpy
Requires-Dist: pandas
Requires-Dist: pysat
Requires-Dist: pysatNASA
Requires-Dist: requests
Requires-Dist: scipy
Requires-Dist: xarray
Provides-Extra: doc
Requires-Dist: myst_parser; extra == "doc"
Requires-Dist: numpydoc; extra == "doc"
Requires-Dist: pyproject_parser; extra == "doc"
Requires-Dist: pysat>=3.2.1; extra == "doc"
Requires-Dist: sphinx>=1.3; extra == "doc"
Requires-Dist: sphinx-autoapi; extra == "doc"
Requires-Dist: sphinx-rtd-theme; extra == "doc"
Provides-Extra: test
Requires-Dist: coverage[toml]; extra == "test"
Requires-Dist: flake8; extra == "test"
Requires-Dist: packaging; extra == "test"
Requires-Dist: requests; extra == "test"
Dynamic: license-file
